volumesh/FastGeometryLoader.py
volumesh/GLTFMeshSequence.py
volumesh/Volumesh.py
volumesh/__init__.py
volumesh/__main__.py
volumesh/utils.py
volumesh-1.5.0.dist-info/licenses/LICENSE
volumesh-1.5.0.dist-info/METADATA
volumesh-1.5.0.dist-info/WHEEL
volumesh-1.5.0.dist-info/entry_points.txt
volumesh-1.5.0.dist-info/top_level.txt
volumesh-1.5.0.dist-info/RECORD
