Metadata-Version: 2.4
Name: volumesh
Version: 1.5.0
Summary: Utility for creating volumetric mesh container files in glTF format.
Home-page: https://github.com/cansik/volumesh
Author: Florian Bruggisser
Author-email: github@broox.ch
License: MIT License
License-File: LICENSE
Requires-Dist: wheel
Requires-Dist: open3d~=0.19
Requires-Dist: tqdm
Requires-Dist: opencv-python
Requires-Dist: pygltflib~=1.16.5
Provides-Extra: draco
Requires-Dist: DracoPy~=1.5.0; extra == "draco"
Provides-Extra: all
Requires-Dist: DracoPy~=1.5.0; extra == "all"
Dynamic: author
Dynamic: author-email
Dynamic: description
Dynamic: description-content-type
Dynamic: home-page
Dynamic: license
Dynamic: license-file
Dynamic: provides-extra
Dynamic: requires-dist
Dynamic: summary
